Makefile
README.md
ig/__init__.py
ig/colors.py
ig/graph.py
ig/main.py
ig/paths.py
ig/serve.py
ig/walk.py
ig_cpp-0.1.9.dist-info/DESCRIPTION.rst
ig_cpp-0.1.9.dist-info/METADATA
ig_cpp-0.1.9.dist-info/RECORD
ig_cpp-0.1.9.dist-info/WHEEL
ig_cpp-0.1.9.dist-info/entry_points.txt
ig_cpp-0.1.9.dist-info/metadata.json
ig_cpp-0.1.9.dist-info/top_level.txt
scripts/__init__.py
scripts/bump.py
www/graph.html
www/graph.js
www/graph.json
www/style.css
www/sigma/LICENSE.txt
www/sigma/README.md
www/sigma/sigma.canvas.edges.curvedArrow.js
www/sigma/sigma.canvas.labels.def.js
www/sigma/sigma.layout.forceAtlas2.min.js
www/sigma/sigma.min.js
www/sigma/sigma.parsers.json.min.js
www/sigma/sigma.plugins.dragNodes.min.js
www/sigma/sigma.plugins.filter.min.js
