Metadata-Version: 2.0
Name: ig-cpp
Version: 0.1.9
Summary: A tool to visualize include graphs for C++ projects
Home-page: https://github.com/goldsborough/ig
Author: Peter Goldsborough
Author-email: peter@goldsborough.me
License: MIT
Keywords: visualization C++ tool
Platform: UNKNOWN
Classifier: Development Status :: 5 - Production/Stable
Classifier: Intended Audience :: Developers
Classifier: Topic :: Software Development
Classifier: License :: OSI Approved :: MIT License
Classifier: Programming Language :: Python
Classifier: Programming Language :: Python :: 2
Classifier: Programming Language :: Python :: 2.6
Classifier: Programming Language :: Python :: 2.7
Classifier: Programming Language :: Python :: 3
Classifier: Programming Language :: Python :: 3.2
Classifier: Programming Language :: Python :: 3.3
Classifier: Programming Language :: Python :: 3.4
Classifier: Programming Language :: Python :: 3.5
